flake8_nb/__init__.py
flake8_nb/__main__.py
flake8_nb/flake8_integration/__init__.py
flake8_nb/flake8_integration/cli.py
flake8_nb/flake8_integration/formatter.py
flake8_nb/parsers/__init__.py
flake8_nb/parsers/cell_parsers.py
flake8_nb/parsers/notebook_parsers.py
flake8_nb-0.5.3.dist-info/LICENSE
flake8_nb-0.5.3.dist-info/METADATA
flake8_nb-0.5.3.dist-info/WHEEL
flake8_nb-0.5.3.dist-info/entry_points.txt
flake8_nb-0.5.3.dist-info/top_level.txt
flake8_nb-0.5.3.dist-info/RECORD
