Metadata-Version: 2.1
Name: flake8-nb
Version: 0.5.3
Summary: Flake8 based checking for jupyter notebooks
Home-page: https://github.com/s-weigand/flake8-nb
Author: Sebastian Weigand
Author-email: s.weigand.phy@gmail.com
License: Apache-2.0
Project-URL: Documentation, https://flake8-nb.readthedocs.io/en/latest/
Project-URL: Source, https://github.com/s-weigand/flake8-nb
Project-URL: Tracker, https://github.com/s-weigand/flake8-nb/issues
Project-URL: Changelog, https://flake8-nb.readthedocs.io/en/latest/changelog.html
Keywords: flake8_nb flake8 lint notebook jupyter ipython
Platform: any
Classifier: Development Status :: 4 - Beta
Classifier: Environment :: Console
Classifier: Framework :: Flake8
Classifier: Framework :: Jupyter
Classifier: Intended Audience :: Developers
Classifier: License :: OSI Approved :: Apache Software License
Classifier: Natural Language :: English
Classifier: Operating System :: OS Independent
Classifier: Programming Language :: Python :: 3
Classifier: Programming Language :: Python :: 3 :: Only
Classifier: Programming Language :: Python :: 3.7
Classifier: Programming Language :: Python :: 3.8
Classifier: Programming Language :: Python :: 3.9
Classifier: Programming Language :: Python :: 3.10
Classifier: Programming Language :: Python :: 3.11
Classifier: Programming Language :: Python :: Implementation :: CPython
Classifier: Topic :: Software Development :: Libraries :: Python Modules
Classifier: Topic :: Software Development :: Quality Assurance
Requires-Python: >=3.7
Requires-Dist: flake8 (<5.0.5,>=3.8.0)
Requires-Dist: ipython (>=7.8.0)
Requires-Dist: nbconvert (>=5.6.0)
